src/multiplier_fast.v
// multiplier_fast.v
// 8-bit multiplier using a balanced adder-tree over partial products.
// This reduces the addition depth compared to a naive linear sum of partial products,
// giving much better timing in practice.  Functionally equivalent to a Wallace-like
// reduction for this bit-width, and easy to extend/replace with CSAs/CLAs later.

module multiplier_fast (
    input  [7:0] a,
    input  [7:0] b,
    output [15:0] product
);

    // Partial products (each shifted into a 16-bit vector)
    wire [15:0] pp0 = (b[0]) ? {8'b0, a}        : 16'b0;
    wire [15:0] pp1 = (b[1]) ? {7'b0, a, 1'b0}  : 16'b0;
    wire [15:0] pp2 = (b[2]) ? {6'b0, a, 2'b0}  : 16'b0;
    wire [15:0] pp3 = (b[3]) ? {5'b0, a, 3'b0}  : 16'b0;
    wire [15:0] pp4 = (b[4]) ? {4'b0, a, 4'b0}  : 16'b0;
    wire [15:0] pp5 = (b[5]) ? {3'b0, a, 5'b0}  : 16'b0;
    wire [15:0] pp6 = (b[6]) ? {2'b0, a, 6'b0}  : 16'b0;
    wire [15:0] pp7 = (b[7]) ? {1'b0, a, 7'b0}  : 16'b0;

    // Balanced adder tree (pairwise additions -> pairwise -> final)
    wire [15:0] s0 = pp0 + pp1;
    wire [15:0] s1 = pp2 + pp3;
    wire [15:0] s2 = pp4 + pp5;
    wire [15:0] s3 = pp6 + pp7;

    wire [15:0] t0 = s0 + s1;  // combines pp0..pp3
    wire [15:0] t1 = s2 + s3;  // combines pp4..pp7

    assign product = t0 + t1;  // final combination (balanced)
endmodule

tb/tb_multiplier_fast.v
`timescale 1ns/1ps

module tb_multiplier_fast;
    reg  [7:0] a, b;
    wire [15:0] product;

    multiplier_fast DUT (.a(a), .b(b), .product(product));

    integer i, j;

    initial begin
        $dumpfile("waves/multiplier_fast.vcd");
        $dumpvars(0, tb_multiplier_fast);
        // Some directed tests
        // a = 8'd0;   b = 8'd0;    #10;
        a = 8'd1;   b = 8'd255;  #10;
        a = 8'd5;   b = 8'd10;   #10;
        a = 8'd15;  b = 8'd15;   #10;
        a = 8'd127; b = 8'd2;    #10;
        a = 8'd255; b = 8'd255;  #10;

        // Random exhaustive-ish tests (not full 65536 but many)
        for (i = 0; i < 2000; i = i + 1) begin
            a = $random % 256;
            b = $random % 256;
            #1;
            if (product !== (a * b)) begin
                $display("ERROR: a=%0d b=%0d product=%0d expected=%0d", a, b, product, a*b);
                $finish;
            end
            #4;
        end

        $display("All random checks passed.");
        $finish;
    end
endmodule

waves/multiplier_fast.vcd
$date
	Sun Nov 16 20:29:29 2025
$end
$version
	Icarus Verilog
$end
$timescale
	1ps
$end
$scope module tb_multiplier_fast $end
$var wire 16 ! product [15:0] $end
$var reg 8 " a [7:0] $end
$var reg 8 # b [7:0] $end
$var integer 32 $ i [31:0] $end
$scope module DUT $end
$var wire 8 % a [7:0] $end
$var wire 8 & b [7:0] $end
$var wire 16 ' t1 [15:0] $end
$var wire 16 ( t0 [15:0] $end
$var wire 16 ) s3 [15:0] $end
$var wire 16 * s2 [15:0] $end
$var wire 16 + s1 [15:0] $end
$var wire 16 , s0 [15:0] $end
$var wire 16 - product [15:0] $end
$var wire 16 . pp7 [15:0] $end
$var wire 16 / pp6 [15:0] $end
$var wire 16 0 pp5 [15:0] $end
$var wire 16 1 pp4 [15:0] $end
$var wire 16 2 pp3 [15:0] $end
$var wire 16 3 pp2 [15:0] $end
$var wire 16 4 pp1 [15:0] $end
$var wire 16 5 pp0 [15:0] $end
$upscope $end
$upscope $end
$enddefinitions $end
$comment Show the parameter values. $end
$dumpall
$end
#0
$dumpvars
b1 5
b10 4
b100 3
b1000 2
b10000 1
b100000 0
b1000000 /
b10000000 .
b11111111 -
b11 ,
b1100 +
b110000 *
b11000000 )
b1111 (
b11110000 '
b11111111 &
b1 %
bx $
b11111111 #
b1 "
b11111111 !
$end
#10000
b0 5
b1010 ,
b1010 4
b0 3
b110010 (
b101000 +
b101000 2
b0 1
b0 *
b0 0
b0 /
b110010 !
b110010 -
b0 '
b0 )
b0 .
b1010 #
b1010 &
b101 "
b101 %
#20000
b1111 5
b111100 3
b101101 ,
b11110 4
b11100001 !
b11100001 -
b11100001 (
b10110100 +
b1111000 2
b1111 #
b1111 &
b1111 "
b1111 %
#30000
b0 5
b11111110 ,
b11111110 4
b0 3
b11111110 !
b11111110 -
b11111110 (
b0 +
b0 2
b10 #
b10 &
b1111111 "
b1111111 %
#40000
b11111111 5
b1111111100 3
b101111110100 +
b11111111000 2
b111111110000 1
b10111111010000 *
b1111111100000 0
b11111111000000 /
b1110111100010000 '
b1011111101000000 )
b111111110000000 .
b1111111000000001 !
b1111111000000001 -
b111011110001 (
b1011111101 ,
b111111110 4
b11111111 #
b11111111 &
b11111111 "
b11111111 %
#50000
b100100 5
b100100 ,
b0 4
b0 3
b100100 (
b0 +
b0 2
b0 1
b0 *
b0 0
b0 /
b1001000100100 !
b1001000100100 -
b1001000000000 '
b1001000000000 )
b1001000000000 .
b10000001 #
b10000001 &
b100100 "
b100100 %
b0 $
#55000
b10010 4
b100100000 *
b100100000 0
b1001000000 /
b11011 (
b11011 ,
b1001 5
b1101111011 !
b1101111011 -
b1101100000 '
b1001000000 )
b0 .
b1100011 #
b1100011 &
b1001 "
b1001 %
b1 $
#60000
b110100 3
b10011100 +
b1101000 2
b11010000000 .
b1101 5
b10101001 (
b1101 ,
b0 4
b0 *
b0 0
b11100101001 !
b11100101001 -
b11010000000 '
b11010000000 )
b0 /
b10001101 #
b10001101 &
b1101 "
b1101 %
b10 $
#65000
b11001010 4
b11001010000 *
b11001010000 1
b11001010 ,
b0 5
b0 3
b11001010 (
b0 +
b0 2
b11100011010 !
b11100011010 -
b11001010000 '
b0 )
b0 .
b10010 #
b10010 &
b1100101 "
b1100101 %
b11 $
#70000
b1 5
b100 3
b1100 +
b1000 2
b1101 (
b1 ,
b0 4
b1101 !
b1101 -
b0 '
b0 *
b0 1
b1101 #
b1101 &
b1 "
b1 %
b100 $
#75000
b11101100000 1
b1011000100000 '
b1011000100000 *
b111011000000 0
b1110110 ,
b1110110 5
b111011000 3
b1110000011110 !
b1110000011110 -
b10111111110 (
b10110001000 +
b1110110000 2
b111101 #
b111101 &
b1110110 "
b1110110 %
b101 $
#80000
b111011010000000 )
b111011010000000 .
b0 ,
b0 5
b1110110100 3
b101100011100 (
b101100011100 +
b11101101000 2
b0 1
b1000000110011100 !
b1000000110011100 -
b111011010000000 '
b0 *
b0 0
b10001100 #
b10001100 &
b11101101 "
b11101101 %
b110 $
#85000
b111110010 ,
b111110010 4
b11111001000000 /
b1111100100 3
b10111010110 (
b1111100100 +
b0 2
b1100000010010110 !
b1100000010010110 -
b1011101011000000 '
b1011101011000000 )
b111110010000000 .
b11000110 #
b11000110 &
b11111001 "
b11111001 %
b111 $
#90000
b11000101000 2
b1100010100000 *
b1100010100000 0
b110001010 ,
b110001010 4
b11110110010 (
b11000101000 +
b0 3
b0 /
b1000001011010010 !
b1000001011010010 -
b111101100100000 '
b110001010000000 )
b110001010000000 .
b10101010 #
b10101010 &
b11000101 "
b11000101 %
b1000 $
#95000
b11100101 5
b1110010100 3
b111001010000 1
b11100101000000 /
b1010101111 ,
b111001010 4
b11001000011 (
b1110010100 +
b0 2
b10101011110000 *
b1110010100000 0
b110101001110011 !
b110101001110011 -
b110010000110000 '
b11100101000000 )
b0 .
b1110111 #
b1110111 &
b11100101 "
b11100101 %
b1001 $
#100000
b10010000 2
b100100000000 .
b10010 5
b110110 ,
b100100 4
b100001110 (
b11011000 +
b1001000 3
b0 1
b0 *
b0 0
b101000001110 !
b101000001110 -
b100100000000 '
b100100000000 )
b0 /
b10001111 #
b10001111 &
b10010 "
b10010 %
b1010 $
#105000
b11110010000000 /
b0 5
b111100100 ,
b111100100 4
b1111001000 3
b110100111100 (
b101101011000 +
b11110010000 2
b1100001010111100 !
b1100001010111100 -
b1011010110000000 '
b1011010110000000 )
b111100100000000 .
b11001110 #
b11001110 &
b11110010 "
b11110010 %
b1011 $
#110000
b11101000 5
b11101000 ,
b0 4
b1110100000 3
b10010001000 (
b1110100000 +
b0 2
b11101000000000 /
b1011001010001000 !
b1011001010001000 -
b1010111000000000 '
b1010111000000000 )
b111010000000000 .
b11000101 #
b11000101 &
b11101000 "
b11101000 %
b1100 $
#115000
b1011100000 2
b10111000000 1
b1000101000000 *
b101110000000 0
b1011100 ,
b1011100 5
b10010101100 (
b10001010000 +
b101110000 3
b0 /
b100001111101100 !
b100001111101100 -
b11111101000000 '
b10111000000000 )
b10111000000000 .
b10111101 #
b10111101 &
b1011100 "
b1011100 %
b1101 $
#120000
b101101000000 /
b101101 ,
b101101 5
b10110100 3
b11100001 (
b10110100 +
b0 2
b0 1
b10110100000 *
b10110100000 0
b1000111000001 !
b1000111000001 -
b1000011100000 '
b101101000000 )
b0 .
b1100101 #
b1100101 &
b101101 "
b101101 %
b1110 $
#125000
b11000110 4
b1100011000 2
b11000110 ,
b0 5
b1111011110 (
b1100011000 +
b0 3
b0 *
b0 0
b1111011110 !
b1111011110 -
b0 '
b0 )
b0 /
b1010 #
b1010 &
b1100011 "
b1100011 %
b1111 $
#130000
b1000000000000 '
b1000000000000 *
b1000000000000 0
b0 ,
b0 4
b1000000000000 !
b1000000000000 -
b0 (
b0 +
b0 2
b100000 #
b100000 &
b10000000 "
b10000000 %
b10000 $
#135000
b10101010 ,
b10101010 5
b1010101000 3
b100010100010 (
b11111111000 +
b10101010000 2
b101010100000 1
b101010100000000 )
b101010100000000 .
b110100001000010 !
b110100001000010 -
b101111110100000 '
b101010100000 *
b0 0
b10011101 #
b10011101 &
b10101010 "
b10101010 %
b10001 $
#140000
b100101100 4
b111000010 ,
b10010110 5
b0 3
b111000010 (
b0 +
b0 2
b100101100000 *
b100101100000 1
b101100100010 !
b101100100010 -
b100101100000 '
b0 )
b0 .
b10011 #
b10011 &
b10010110 "
b10010110 %
b10010 $
#145000
b1101000000 )
b1101000000 /
b1101 5
b100111 (
b100111 ,
b11010 4
b10000110111 !
b10000110111 -
b10000010000 '
b11010000 *
b11010000 1
b1010011 #
b1010011 &
b1101 "
b1101 %
b10011 $
#150000
b110101100 +
b110101100 3
b11010110000000 .
b1101011 5
b1000010111 (
b1101011 ,
b0 4
b11010110000 *
b11010110000 1
b101100100000111 !
b101100100000111 -
b101011011110000 '
b101000001000000 )
b1101011000000 /
b11010101 #
b11010101 &
b1101011 "
b1101011 %
b10100 $
#155000
b100 4
b10000 2
b1000000 0
b100 ,
b0 5
b11100 (
b11000 +
b1000 3
b1000000 *
b0 1
b0 /
b101011100 !
b101011100 -
b101000000 '
b100000000 )
b100000000 .
b10101110 #
b10101110 &
b10 "
b10 %
b10101 $
#160000
b11101 5
b11101000000 /
b1010111 ,
b111010 4
b1110100 3
b110110011 (
b101011100 +
b11101000 2
b0 *
b0 0
b1011101110011 !
b1011101110011 -
b1010111000000 '
b1010111000000 )
b111010000000 .
b11001111 #
b11001111 &
b11101 "
b11101 %
b10110 $
#165000
b0 5
b1000110 ,
b1000110 4
b0 3
b101011110 (
b100011000 +
b100011000 2
b0 /
b101011110 !
b101011110 -
b0 '
b0 )
b0 .
b1010 #
b1010 &
b100011 "
b100011 %
b10111 $
#170000
b1100101000 3
b110010100000 1
b10010111100000 '
b10010111100000 *
b1100101000000 0
b0 ,
b0 4
b10111101011000 !
b10111101011000 -
b100101111000 (
b100101111000 +
b11001010000 2
b111100 #
b111100 &
b11001010 "
b11001010 %
b11000 $
#175000
b111100100 ,
b111100100 4
b111100100000000 )
b111100100000000 .
b0 3
b100101110100 (
b11110010000 +
b11110010000 2
b0 1
b1000001001110100 !
b1000001001110100 -
b111100100000000 '
b0 *
b0 0
b10001010 #
b10001010 &
b11110010 "
b11110010 %
b11001 $
#180000
b10000010000 *
b10000010000 1
b1000001000000 /
b0 ,
b0 4
b1000001000 (
b1000001000 +
b1000001000 2
b11011011011000 !
b11011011011000 -
b11010011010000 '
b11000011000000 )
b10000010000000 .
b11011000 #
b11011000 &
b1000001 "
b1000001 %
b11010 $
#185000
b1111000 ,
b1111000 5
b10000111000 (
b1111000000 +
b1111000000 2
b0 *
b0 1
b0 /
b100000000111000 !
b100000000111000 -
b11110000000000 '
b11110000000000 )
b11110000000000 .
b10001001 #
b10001001 &
b1111000 "
b1111000 %
b11011 $
#190000
b111010110 4
b1110101100 3
b111010110000 1
b10110000010000 *
b1110101100000 0
b111010110 ,
b0 5
b10110000010 (
b1110101100 +
b0 2
b1010011100010010 !
b1010011100010010 -
b1010000110010000 '
b111010110000000 )
b111010110000000 .
b10110110 #
b10110110 &
b11101011 "
b11101011 %
b11100 $
#195000
b11000110000 2
b110001100 ,
b110001100 4
b101011010100 (
b100101001000 +
b1100011000 3
b0 1
b1100011000000 *
b1100011000000 0
b1000011010010100 !
b1000011010010100 -
b111101111000000 '
b110001100000000 )
b110001100000000 .
b10101110 #
b10101110 &
b11000110 "
b11000110 %
b11101 $
#200000
b101111000 ,
b101111000 4
b0 3
b11101011000 (
b10111100000 +
b10111100000 2
b1011110000000 *
b1011110000000 0
b1111011011000 !
b1111011011000 -
b1011110000000 '
b0 )
b0 .
b101010 #
b101010 &
b10111100 "
b10111100 %
b11110 $
#205000
b1011 5
b10110000 1
b1011000000 )
b1011000000 /
b1011 ,
b0 4
b1011 (
b0 +
b0 2
b10011011011 !
b10011011011 -
b10011010000 '
b1000010000 *
b101100000 0
b1110001 #
b1110001 &
b1011 "
b1011 %
b11111 $
#210000
b100001010 4
b1000010100 3
b11000111100 +
b10000101000 2
b11111001011 (
b110001111 ,
b10000101 5
b0 1
b0 *
b0 0
b10100100001011 !
b10100100001011 -
b10000101000000 '
b10000101000000 )
b10000101000000 /
b1001111 #
b1001111 &
b10000101 "
b10000101 %
b100000 $
#215000
b1110110000 1
b101100010000 *
b11101100000 0
b0 5
b1110110 ,
b1110110 4
b0 3
b1001001110 (
b111011000 +
b111011000 2
b110101011110 !
b110101011110 -
b101100010000 '
b0 )
b0 /
b111010 #
b111010 &
b111011 "
b111011 %
b100001 $
#220000
b1111110 5
b111111000 3
b1111110 ,
b0 4
b1001110110 (
b111111000 +
b0 2
b11111100000 1
b101001010110 !
b101001010110 -
b11111100000 '
b11111100000 *
b0 0
b10101 #
b10101 &
b1111110 "
b1111110 %
b100010 $
#225000
b11110001000 2
b11110001000000 /
b1011010011000000 )
b111100010000000 .
b11110001 ,
b11110001 5
b100001111001 (
b11110001000 +
b0 3
b1100110001001001 !
b1100110001001001 -
b1100001111010000 '
b111100010000 *
b111100010000 1
b11011001 #
b11011001 &
b11110001 "
b11110001 %
b100011 $
#230000
b110001000 3
b0 ,
b0 5
b10010011000 (
b10010011000 +
b1100010000 2
b0 *
b0 1
b1100010000000 /
b1110100011000 !
b1110100011000 -
b1100010000000 '
b1100010000000 )
b0 .
b1001100 #
b1001100 &
b1100010 "
b1100010 %
b100100 $
#235000
b10011111 5
b111011101 ,
b100111110 4
b100111110000000 .
b1001111100 3
b100101010001 (
b11101110100 +
b10011111000 2
b101100011010001 !
b101100011010001 -
b100111110000000 '
b100111110000000 )
b0 /
b10001111 #
b10001111 &
b10011111 "
b10011111 %
b100101 $
#240000
b111110000000 1
b10111010000000 *
b1111100000000 0
b11111000 5
b1011101000 ,
b111110000 4
b1111100000 3
b11011001000 (
b1111100000 +
b0 2
b1011000101001000 !
b1011000101001000 -
b1010101010000000 '
b111110000000000 )
b111110000000000 .
b10110111 #
b10110111 &
b11111000 "
b11111000 %
b100110 $
#245000
b10011111000 2
b10011111000000 /
b0 5
b0 ,
b0 4
b11101110100 (
b11101110100 +
b1001111100 3
b100111110000 1
b100111110000 *
b0 0
b11100100100100 !
b11100100100100 -
b11000110110000 '
b10011111000000 )
b0 .
b1011100 #
b1011100 &
b10011111 "
b10011111 %
b100111 $
#250000
b1011011 ,
b1011011 5
b10110110000000 .
b0 3
b1100110011 (
b1011011000 +
b1011011000 2
b0 *
b0 1
b11000010110011 !
b11000010110011 -
b10110110000000 '
b10110110000000 )
b0 /
b10001001 #
b10001001 &
b1011011 "
b1011011 %
b101000 $
#255000
b10010010000 *
b10010010000 1
b1001001000000 /
b0 ,
b0 5
b0 (
b0 +
b0 2
b11101101010000 !
b11101101010000 -
b11101101010000 '
b11011011000000 )
b10010010000000 .
b11010000 #
b11010000 &
b1001001 "
b1001001 %
b101001 $
#260000
b11010111 (
b11010111 ,
b11010111 5
b110101110000 *
b110101110000 1
b11010111000000 /
b100010000000111 !
b100010000000111 -
b100001100110000 '
b11010111000000 )
b0 .
b1010001 #
b1010001 &
b11010111 "
b11010111 %
b101010 $
#265000
b1001011000 3
b11100001000 +
b10010110000 2
b11100001000 (
b0 ,
b0 5
b0 *
b0 1
b11100001000 !
b11100001000 -
b0 '
b0 )
b0 /
b1100 #
b1100 &
b10010110 "
b10010110 %
b101011 $
#270000
b11000010000000 /
b1001000110000000 '
b1001000110000000 )
b110000100000000 .
b0 3
b1001011110010000 !
b1001011110010000 -
b11000010000 (
b11000010000 +
b11000010000 2
b11001000 #
b11001000 &
b11000010 "
b11000010 %
b101100 $
#275000
b1110111 ,
b1110111 5
b111011100 3
b11101110000 1
b1011001010000 *
b111011100000 0
b11000001011 (
b10110010100 +
b1110111000 2
b0 /
b1110001011011 !
b1110001011011 -
b1011001010000 '
b0 )
b0 .
b111101 #
b111101 &
b1110111 "
b1110111 %
b101101 $
#280000
b100100 4
b10010000000 )
b10010000000 /
b100100 ,
b0 5
b1001000 3
b11111100 (
b11011000 +
b10010000 2
b100100000 1
b100011011100 !
b100011011100 -
b11111100000 '
b1101100000 *
b1001000000 0
b1111110 #
b1111110 &
b10010 "
b10010 %
b101110 $
#285000
b1101101 5
b1101101 ,
b0 4
b0 3
b1111010101 (
b1101101000 +
b1101101000 2
b11011010000 1
b1010001110000 *
b110110100000 0
b1100001000101 !
b1100001000101 -
b1010001110000 '
b0 )
b0 /
b111001 #
b111001 &
b1101101 "
b1101101 %
b101111 $
#290000
b111110 4
b11111000000 /
b1011101000000 )
b111110000000 .
b1011101 ,
b11111 5
b1011101 (
b0 +
b0 2
b111110000 1
b1100110001101 !
b1100110001101 -
b1100100110000 '
b111110000 *
b0 0
b11010011 #
b11010011 &
b11111 "
b11111 %
b110000 $
#295000
b10000101000 +
b10000101000 2
b1000010100000 0
b0 5
b10000101000 (
b0 ,
b0 4
b1100011110000 *
b100001010000 1
b10000101000000 /
b11111001011000 !
b11111001011000 -
b11101000110000 '
b10000101000000 )
b0 .
b1111000 #
b1111000 &
b10000101 "
b10000101 %
b110001 $
#300000
b1011011 ,
b1011011 5
b1100110011 (
b1011011000 +
b1011011000 2
b0 1
b0 *
b0 0
b1100111110011 !
b1100111110011 -
b1011011000000 '
b1011011000000 )
b1011011000000 /
b1001001 #
b1001001 &
b1011011 "
b1011011 %
b110010 $
#305000
b1111110 4
b11111100000 *
b11111100000 0
b1111110 ,
b0 5
b1001110110 (
b111111000 +
b111111000 2
b101001010110 !
b101001010110 -
b11111100000 '
b0 )
b0 /
b101010 #
b101010 &
b111111 "
b111111 %
b110011 $
#310000
b101100000 3
b10110000000000 )
b10110000000000 .
b10110000 ,
b10110000 4
b1000010000 (
b101100000 +
b0 2
b10111000010000 !
b10111000010000 -
b10110000000000 '
b0 *
b0 0
b10000110 #
b10000110 &
b1011000 "
b1011000 %
b110100 $
#315000
b10001110000 2
b100011100000 *
b100011100000 1
b0 ,
b0 4
b11010101000 (
b11010101000 +
b1000111000 3
b101011010001000 !
b101011010001000 -
b100111111100000 '
b100011100000000 )
b100011100000000 .
b10011100 #
b10011100 &
b10001110 "
b10001110 %
b110101 $
#320000
b111110100 ,
b111110100 4
b1111101000000 0
b1111101000 3
b10111011100 (
b1111101000 +
b0 2
b1111101000000 *
b0 1
b10010100011100 !
b10010100011100 -
b1111101000000 '
b0 )
b0 .
b100110 #
b100110 &
b11111010 "
b11111010 %
b110110 $
#325000
b1110011 5
b11100110000000 )
b11100110000000 .
b101011001 ,
b11100110 4
b101011001 (
b0 +
b0 3
b100100100111001 !
b100100100111001 -
b100011111100000 '
b111001100000 *
b111001100000 0
b10100011 #
b10100011 &
b1110011 "
b1110011 %
b110111 $
#330000
b1011110000 1
b101111 5
b10001101 (
b10001101 ,
b1011110 4
b100011010000 *
b10111100000 0
b10000011011101 !
b10000011011101 -
b10000001010000 '
b1011110000000 )
b1011110000000 .
b10110011 #
b10110011 &
b101111 "
b101111 %
b111000 $
#335000
b101111100 +
b101111100 3
b1011111000000 /
b0 5
b101111100 (
b0 ,
b0 4
b0 1
b0 *
b0 0
b1100100111100 !
b1100100111100 -
b1011111000000 '
b1011111000000 )
b0 .
b1000100 #
b1000100 &
b1011111 "
b1011111 %
b111001 $
#340000
b11110111 5
b1011100101 ,
b111101110 4
b11110111000 2
b111101110000000 .
b101010011101 (
b11110111000 +
b0 3
b1100001111011101 !
b1100001111011101 -
b1011100101000000 '
b1011100101000000 )
b11110111000000 /
b11001011 #
b11001011 &
b11110111 "
b11110111 %
b111010 $
#345000
b111001100000 *
b111001100000 1
b0 5
b111001100 ,
b111001100 4
b100011111100 (
b11100110000 +
b11100110000 2
b11100110000000 /
b101000011011100 !
b101000011011100 -
b100011111100000 '
b11100110000000 )
b0 .
b1011010 #
b1011010 &
b11100110 "
b11100110 %
b111011 $
#350000
b101001 5
b10100100 3
b10100100000 0
b1010010000000 .
b101001 ,
b0 4
b1000010101 (
b111101100 +
b101001000 2
b10100100000 *
b0 1
b10010111110101 !
b10010111110101 -
b10001111100000 '
b1111011000000 )
b101001000000 /
b11101101 #
b11101101 &
b101001 "
b101001 %
b111100 $
#355000
b11011010 ,
b11011010 5
b1101101000 3
b10001000010 (
b1101101000 +
b0 2
b1101101000000 *
b1101101000000 0
b11011010000000 /
b101011000000010 !
b101011000000010 -
b101000111000000 '
b11011010000000 )
b0 .
b1100101 #
b1100101 &
b11011010 "
b11011010 %
b111101 $
#360000
b101101010 4
b10110101000 2
b101101010000 1
b101101010000000 .
b1000011111 ,
b10110101 5
b101010011011 (
b100001111100 +
b1011010100 3
b101101010000 *
b0 0
b1001110110101011 !
b1001110110101011 -
b1001001100010000 '
b1000011111000000 )
b10110101000000 /
b11011111 #
b11011111 &
b10110101 "
b10110101 %
b111110 $
#365000
b0 5
b0 ,
b0 4
b111100100 3
b111100100 (
b111100100 +
b0 2
b0 *
b0 1
b1111001000000 /
b10000000100100 !
b10000000100100 -
b1111001000000 '
b1111001000000 )
b0 .
b1000100 #
b1000100 &
b1111001 "
b1111001 %
b111111 $
#370000
b110100000 ,
b110100000 4
b11010000000 2
b1101000000000 *
b1101000000000 0
b100000100000 (
b11010000000 +
b0 3
b10001000100000 !
b10001000100000 -
b1101000000000 '
b0 )
b0 /
b101010 #
b101010 &
b11010000 "
b11010000 %
b1000000 $
#375000
b1010101100 3
b101010110 ,
b101010110 4
b100101011010 (
b100000000100 +
b10101011000 2
b100101011010 !
b100101011010 -
b0 '
b0 *
b0 0
b1110 #
b1110 &
b10101011 "
b10101011 %
b1000001 $
#380000
b110111000000 *
b110111000000 1
b111101111000000 '
b110111000000000 )
b110111000000000 .
b110111000 ,
b110111000 4
b0 3
b1000010001011000 !
b1000010001011000 -
b100010011000 (
b11011100000 +
b11011100000 2
b10011010 #
b10011010 &
b11011100 "
b11011100 %
b1000010 $
#385000
b11111101 5
b11111101000000 /
b1011110111 ,
b111111010 4
b1011110111 (
b0 +
b0 2
b0 *
b0 1
b1100000010110111 !
b1100000010110111 -
b1011110111000000 '
b1011110111000000 )
b111111010000000 .
b11000011 #
b11000011 &
b11111101 "
b11111101 %
b1000011 $
#390000
b101011000 3
b10000001000 +
b1010110000 2
b0 5
b10010110100 (
b10101100 ,
b10101100 4
b1010110000000 /
b1101000110100 !
b1101000110100 -
b1010110000000 '
b1010110000000 )
b0 .
b1001110 #
b1001110 &
b1010110 "
b1010110 %
b1000100 $
#395000
b11001110 ,
b11001110 4
b0 3
b10000000110 (
b1100111000 +
b1100111000 2
b10000000110 !
b10000000110 -
b0 '
b0 )
b0 /
b1010 #
b1010 &
b1100111 "
b1100111 %
b1000101 $
#400000
b101101100000 1
b10001000100000 '
b10001000100000 *
b1011011000000 0
b0 ,
b0 4
b10011111010000 !
b10011111010000 -
b10110110000 (
b10110110000 +
b10110110000 2
b111000 #
b111000 &
b10110110 "
b10110110 %
b1000110 $
#405000
b11110010000000 )
b11110010000000 .
b1111001000 (
b1111001000 +
b1111001000 2
b11110010000 1
b101011011111000 !
b101011011111000 -
b101001100110000 '
b1011010110000 *
b111100100000 0
b10111000 #
b10111000 &
b1111001 "
b1111001 %
b1000111 $
#410000
b10010100 5
b110111100 ,
b100101000 4
b110111100 (
b0 +
b0 2
b100101000000 1
b100101000000 *
b0 0
b101010011111100 !
b101010011111100 -
b101001101000000 '
b100101000000000 )
b100101000000000 .
b10010011 #
b10010011 &
b10010100 "
b10010100 %
b1001000 $
#415000
b100000 +
b100000 2
b100000000 /
b100 5
b100100 (
b100 ,
b0 4
b1000000 *
b1000000 1
b101100100 !
b101100100 -
b101000000 '
b100000000 )
b0 .
b1011001 #
b1011001 &
b100 "
b100 %
b1001001 $
#420000
b1101101100 3
b11011011 ,
b11011011 5
b101100011111 (
b101001000100 +
b11011011000 2
b0 *
b0 1
b100000111011111 !
b100000111011111 -
b11011011000000 '
b11011011000000 )
b11011011000000 /
b1001101 #
b1001101 &
b11011011 "
b11011011 %
b1001010 $
#425000
b1101100100000 *
b1101100100000 0
b11011001 ,
b11011001 5
b1101100100 3
b101100000101 (
b101000101100 +
b11011001000 2
b101110001100101 !
b101110001100101 -
b101000101100000 '
b11011001000000 )
b11011001000000 /
b1101101 #
b1101101 &
b11011001 "
b11011001 %
b1001011 $
#430000
b11101100 4
b11101100000000 .
b11101100 ,
b0 5
b0 3
b10010011100 (
b1110110000 +
b1110110000 2
b0 *
b0 0
b101110100011100 !
b101110100011100 -
b101100010000000 '
b101100010000000 )
b1110110000000 /
b11001010 #
b11001010 &
b1110110 "
b1110110 %
b1001100 $
#435000
b10110110 5
b1011011000 3
b101101100000 *
b101101100000 1
b10110110 ,
b0 4
b1110001110 (
b1011011000 +
b0 2
b0 /
b110100111101110 !
b110100111101110 -
b110011001100000 '
b101101100000000 )
b101101100000000 .
b10010101 #
b10010101 &
b10110110 "
b10110110 %
b1001101 $
#440000
b0 ,
b0 5
b100011000 (
b100011000 +
b100011000 3
b0 *
b0 1
b100011000 !
b100011000 -
b0 '
b0 )
b0 .
b100 #
b100 &
b1000110 "
b1000110 %
b1001110 $
#445000
b11110111 ,
b11110111 5
b11110111000 2
b1111011100000 *
b1111011100000 0
b101110010100000 '
b11110111000000 )
b11110111000000 /
b110010101001111 !
b110010101001111 -
b100010101111 (
b11110111000 +
b0 3
b1101001 #
b1101001 &
b11110111 "
b11110111 %
b1001111 $
#450000
b101101000000000 .
b0 ,
b0 5
b10110100000 (
b10110100000 +
b10110100000 2
b0 *
b0 0
b101111110100000 !
b101111110100000 -
b101101000000000 '
b101101000000000 )
b0 /
b10001000 #
b10001000 &
b10110100 "
b10110100 %
b1010000 $
#455000
b101000 ,
b101000 5
b10100000 3
b10100000000 *
b10100000000 0
b1000001000 (
b111100000 +
b101000000 2
b11100001000 !
b11100001000 -
b10100000000 '
b0 )
b0 .
b101101 #
b101101 &
b101000 "
b101000 %
b1010001 $
#460000
b110001110 4
b110001110 ,
b0 5
b1100011100 3
b101011100010 (
b100101010100 +
b11000111000 2
b10001111000010 !
b10001111000010 -
b1100011100000 '
b1100011100000 *
b1100011100000 0
b101110 #
b101110 &
b11000111 "
b11000111 %
b1010010 $
#465000
b10000000 1
b0 ,
b0 4
b100000 3
b1100000 (
b1100000 +
b1000000 2
b11100000 !
b11100000 -
b10000000 '
b10000000 *
b0 0
b11100 #
b11100 &
b1000 "
b1000 %
b1010011 $
#470000
b11111101 ,
b11111101 5
b1111110100000 0
b0 3
b100011100101 (
b11111101000 +
b11111101000 2
b10100010000101 !
b10100010000101 -
b1111110100000 '
b1111110100000 *
b0 1
b101001 #
b101001 &
b11111101 "
b11111101 %
b1010100 $
#475000
b111000 4
b1110000 3
b111000000000 )
b111000000000 .
b111000 ,
b0 5
b10101000 (
b1110000 +
b0 2
b111010101000 !
b111010101000 -
b111000000000 '
b0 *
b0 0
b10000110 #
b10000110 &
b11100 "
b11100 %
b1010101 $
#480000
b11011010 5
b11011010000 2
b110110100000 1
b10100011100000 *
b1101101000000 0
b11011010 ,
b0 4
b101100010010 (
b101000111000 +
b1101101000 3
b11001111110010 !
b11001111110010 -
b10100011100000 '
b0 )
b0 .
b111101 #
b111101 &
b11011010 "
b11011010 %
b1010110 $
#485000
b1100110000000 )
b1100110000000 /
b0 ,
b0 5
b0 3
b0 (
b0 +
b0 2
b11001100000 1
b10110010100000 !
b10110010100000 -
b10110010100000 '
b1001100100000 *
b110011000000 0
b1110000 #
b1110000 &
b1100110 "
b1100110 %
b1010111 $
#490000
b11100110 ,
b11100110 4
b10001111110 (
b1110011000 +
b1110011000 2
b11100110000000 .
b11100110000 1
b1010110010000 *
b111001100000 0
b101001110001110 !
b101001110001110 -
b100111100010000 '
b11100110000000 )
b0 /
b10111010 #
b10111010 &
b1110011 "
b1110011 %
b1011000 $
#495000
b1011110000000 /
b10111100 ,
b10111100 4
b1110101100 (
b1011110000 +
b1011110000 2
b10111100000 1
b1000110100000 *
b101111000000 0
b101101111001100 !
b101101111001100 -
b101100000100000 '
b100011010000000 )
b10111100000000 .
b11111010 #
b11111010 &
b1011110 "
b1011110 %
b1011001 $
